odoo8_addon_l10n_br_crm_zip-8.0.1.0.1.99.dev6-py2.7-nspkg.pth
odoo8_addon_l10n_br_crm_zip-8.0.1.0.1.99.dev6.dist-info/METADATA
odoo8_addon_l10n_br_crm_zip-8.0.1.0.1.99.dev6.dist-info/RECORD
odoo8_addon_l10n_br_crm_zip-8.0.1.0.1.99.dev6.dist-info/WHEEL
odoo8_addon_l10n_br_crm_zip-8.0.1.0.1.99.dev6.dist-info/namespace_packages.txt
odoo8_addon_l10n_br_crm_zip-8.0.1.0.1.99.dev6.dist-info/top_level.txt
odoo_addons/l10n_br_crm_zip/README.rst
odoo_addons/l10n_br_crm_zip/__init__.py
odoo_addons/l10n_br_crm_zip/__openerp__.py
odoo_addons/l10n_br_crm_zip/i18n/pt_BR.po
odoo_addons/l10n_br_crm_zip/models/__init__.py
odoo_addons/l10n_br_crm_zip/models/crm_lead.py
odoo_addons/l10n_br_crm_zip/static/description/icon.png
odoo_addons/l10n_br_crm_zip/views/crm_lead_view.xml
odoo_addons/l10n_br_crm_zip/views/crm_opportunity_view.xml
