Metadata-Version: 2.1
Name: odoo8-addon-l10n-br-crm-zip
Version: 8.0.1.0.1.99.dev6
Summary: Brazilian Localization CRM Zip
Home-page: http://odoobrasil.org
Author: Fabio Negrini, Odoo Community Association (OCA)
Author-email: support@odoo-community.org
License: AGPL-3
Platform: UNKNOWN
Classifier: Programming Language :: Python
Classifier: Framework :: Odoo
Classifier: License :: OSI Approved :: GNU Affero General Public License v3
Requires-Python: ~=2.7
Requires-Dist: odoo8-addon-l10n-br-crm
Requires-Dist: odoo8-addon-l10n-br-zip
Requires-Dist: odoo (<9.0a,>=8.0a)
